{
    "apples": [
    { "region": "Hirzenbach", "count": "12627"},
    { "region": "Schwamendingen-Mitte", "count": "11012" },
    { "region": "Saatlen", "count": "8388" },
    { "region": "Seebach", "count": "25817" },
    { "region": "Oerlikon", "count": "22815" },
    { "region": "Affoltern", "count": "26177" },
    { "region": "Wipkingen", "count": "16544" },
    { "region": "Hoengg", "count": "23797" },
    { "region": "Altstetten", "count": "32603" },
    { "region": "Albisrieden", "count": "22113" },
    { "region": "Weinegg", "count": "5248" },
    { "region": "Muehlebach", "count": "6164" },
    { "region": "Seefeld", "count": "5129" },
    { "region": "Witikon", "count": "10600" },
    { "region": "Hirslanden", "count": "7465" },
    { "region": "Hottingen", "count": "11172" },
    { "region": "Fluntern", "count": "8221" },
    { "region": "Oberstrass", "count": "10846" },
    { "region": "Unterstrass", "count": "22768" },
    { "region": "Escher Wyss", "count": "6088" },
    { "region": "Gewerbeschule", "count": "9578" },
    { "region": "Hard", "count": "13057" },
    { "region": "Langstrasse", "count": "11144" },
    { "region": "Werd", "count": "4574" },
    { "region": "Sihlfeld", "count": "21660" },
    { "region": "Friesenberg", "count": "10860" },
    { "region": "Alt-Wiedikon", "count": "17522" },
    { "region": "Enge", "count": "9489" },
    { "region": "Leimbach", "count": "6212" },
    { "region": "Wollishofen", "count": "17892" },
    { "region": "City", "count": "830" },
    { "region": "Lindenhof", "count": "955" },
    { "region": "Hochschulen", "count": "677" },
    { "region": "Rathaus", "count": "3266" }
  ],
	"oranges": [
		{ "region": "North", "count": "200"},
		{ "region": "South", "count": "200"},
		{ "region": "East", "count": "200"},
		{ "region": "West", "count": "200"},
		{ "region": "Central", "count": "200"}
	]
}